sentinet/__init__.py
sentinet/control/__init__.py
sentinet/control/Localizer/CommsTestLocalizer.py
sentinet/control/Localizer/Localizer_Base.py
sentinet/control/Localizer/__init__.py
sentinet/control/StateMachine/RMT_State_Machine.py
sentinet/control/StateMachine/State_Machine_Base.py
sentinet/control/StateMachine/__init__.py
sentinet/control/control/ControlClient.py
sentinet/control/control/__init__.py
sentinet/control/control/main.py
sentinet/core/__init__.py
sentinet/core/control/ControlClient.py
sentinet/core/control/__init__.py
sentinet/core/control/main.py
sentinet/core/control/zmqex.py
sentinet/core/messages/Message.py
sentinet/core/messages/MessageFactory.py
sentinet/core/messages/MessageKeys.py
sentinet/core/messages/__init__.py
sentinet/curmt/KermitControlModule.py
sentinet/curmt/__init__.py
SentiNet-1.0.0.dist-info/LICENSE
SentiNet-1.0.0.dist-info/METADATA
SentiNet-1.0.0.dist-info/WHEEL
SentiNet-1.0.0.dist-info/top_level.txt
SentiNet-1.0.0.dist-info/RECORD
