Metadata-Version: 2.1
Name: SentiNet
Version: 1.0.0
Summary: A Python Sentinet Derivative
Home-page: https://curmc.github.io/
Author: Trace Valade
Author-email: trace.valade@colorado.edu
License: MIT
Platform: UNKNOWN
Classifier: Development Status :: 1 - Planning
Classifier: Intended Audience :: Science/Research
Classifier: License :: OSI Approved :: BSD License
Classifier: Operating System :: POSIX :: Linux
Classifier: Programming Language :: Python :: 2
Classifier: Programming Language :: Python :: 2.7
Classifier: Programming Language :: Python :: 3
Classifier: Programming Language :: Python :: 3.4
Classifier: Programming Language :: Python :: 3.5
Requires-Dist: numpy
Requires-Dist: pyzmq
Requires-Dist: matplotlib
